odoo/addons/shopinvader_product_stock_forecast_expiry/README.rst
odoo/addons/shopinvader_product_stock_forecast_expiry/__init__.py
odoo/addons/shopinvader_product_stock_forecast_expiry/__manifest__.py
odoo/addons/shopinvader_product_stock_forecast_expiry/i18n/shopinvader_product_stock_forecast_expiry.pot
odoo/addons/shopinvader_product_stock_forecast_expiry/models/__init__.py
odoo/addons/shopinvader_product_stock_forecast_expiry/models/shopinvader_backend.py
odoo/addons/shopinvader_product_stock_forecast_expiry/models/shopinvader_variant.py
odoo/addons/shopinvader_product_stock_forecast_expiry/readme/CONFIGURE.rst
odoo/addons/shopinvader_product_stock_forecast_expiry/readme/CONTRIBUTORS.rst
odoo/addons/shopinvader_product_stock_forecast_expiry/readme/DESCRIPTION.rst
odoo/addons/shopinvader_product_stock_forecast_expiry/static/description/index.html
odoo/addons/shopinvader_product_stock_forecast_expiry/tests/__init__.py
odoo/addons/shopinvader_product_stock_forecast_expiry/tests/test_product.py
odoo/addons/shopinvader_product_stock_forecast_expiry/views/shopinvader_backend.xml
odoo14_addon_shopinvader_product_stock_forecast_expiry-14.0.1.0.1.dev4.dist-info/METADATA
odoo14_addon_shopinvader_product_stock_forecast_expiry-14.0.1.0.1.dev4.dist-info/WHEEL
odoo14_addon_shopinvader_product_stock_forecast_expiry-14.0.1.0.1.dev4.dist-info/top_level.txt
odoo14_addon_shopinvader_product_stock_forecast_expiry-14.0.1.0.1.dev4.dist-info/RECORD
