Metadata-Version: 2.1
Name: odoo14-addon-shopinvader_product_stock_forecast_expiry
Version: 14.0.1.0.1.dev4
Summary: Integrates product lot expiration into the forecast
Home-page: https://github.com/shopinvader/odoo-shopinvader
Author: Camptocamp SA
License: AGPL-3
Classifier: Programming Language :: Python
Classifier: Framework :: Odoo
Classifier: Framework :: Odoo :: 14.0
Classifier: License :: OSI Approved :: GNU Affero General Public License v3
Requires-Python: >=3.6
Requires-Dist: odoo14-addon-shopinvader-product-stock-forecast
Requires-Dist: odoo <14.1dev,>=14.0a
